helpr/__init__.py
helpr/cache.py
helpr/cdn.py
helpr/common_utils.py
helpr/decorators.py
helpr/exceptions.py
helpr/format_response.py
helpr/json_encoder.py
helpr/s3_helper.py
helpr/secret_manager.py
helpr/token_service.py
helpr/logging/__init__.py
helpr/logging/config.py
helpr/logging/context.py
helpr/logging/filters.py
helpr/logging/middleware.py
helpr/models/__init__.py
helpr/models/base.py
helpr/models/warehouse/__init__.py
helpr/models/warehouse/bulk_upload_log.py
helpr/models/warehouse/enums.py
helpr/models/warehouse/inventory.py
helpr/models/warehouse/inventory_log.py
helpr/models/warehouse/product_sku.py
helpr/models/warehouse/state_pincode_map.py
helpr/models/warehouse/warehouse.py
helpr/models/warehouse/warehouse_delivery_mode.py
helpr/models/warehouse/warehouse_delivery_mode_pincodes.py
helpr/models/warehouse/warehouse_pincode_delivery_times.py
helpr/models/warehouse/warehouse_servicable_states.py
helpr/session_cache/__init__.py
helpr/session_cache/base.py
helpr/session_cache/config.py
helpr/session_cache/session_cache.py
helpr-0.9.5.dist-info/licenses/LICENSE
helpr-0.9.5.dist-info/METADATA
helpr-0.9.5.dist-info/WHEEL
helpr-0.9.5.dist-info/top_level.txt
helpr-0.9.5.dist-info/RECORD
