Metadata-Version: 2.4
Name: helpr
Version: 0.9.5
Summary: A utility package for Clinikally applications
Home-page: https://github.com/clinikally/helpr
Author: Clinikally
Author-email: dev@clinikally.com
Classifier: Development Status :: 4 - Beta
Classifier: Intended Audience :: Developers
Classifier: License :: OSI Approved :: MIT License
Classifier: Operating System :: OS Independent
Classifier: Programming Language :: Python :: 3
Classifier: Programming Language :: Python :: 3.9
Classifier: Programming Language :: Python :: 3.10
Classifier: Programming Language :: Python :: 3.11
Requires-Python: >=3.9
License-File: LICENSE
Requires-Dist: boto3>=1.35.81
Requires-Dist: botocore>=1.35.81
Requires-Dist: fastapi>=0.115.6
Requires-Dist: redis[asyncio]>=5.0.0
Requires-Dist: Authlib>=1.2.0
Requires-Dist: pydantic==2.10.2
Requires-Dist: typing_extensions>=4.12.2
Requires-Dist: structlog==25.4.0
Requires-Dist: phonenumbers==9.0.5
Requires-Dist: sqlalchemy>=1.4.0
Requires-Dist: psycopg2-binary>=2.9.0
Dynamic: author
Dynamic: author-email
Dynamic: classifier
Dynamic: description-content-type
Dynamic: home-page
Dynamic: license-file
Dynamic: requires-dist
Dynamic: requires-python
Dynamic: summary
